praisonai_mcp/__init__.py
praisonai_mcp/__main__.py
praisonai_mcp/server.py
praisonai_mcp/tools.py
praisonai_mcp-0.1.0.dist-info/METADATA
praisonai_mcp-0.1.0.dist-info/WHEEL
praisonai_mcp-0.1.0.dist-info/entry_points.txt
praisonai_mcp-0.1.0.dist-info/licenses/LICENSE
praisonai_mcp-0.1.0.dist-info/RECORD
