Metadata-Version: 2.4
Name: praisonai-mcp
Version: 0.1.0
Summary: MCP server that exposes PraisonAI tools for Claude Desktop, Cursor, and other MCP clients
Project-URL: Homepage, https://github.com/MervinPraison/praisonai-mcp
Project-URL: Documentation, https://docs.praison.ai/mcp
Project-URL: Repository, https://github.com/MervinPraison/praisonai-mcp
Project-URL: Issues, https://github.com/MervinPraison/praisonai-mcp/issues
Author-email: Mervin Praison <mervin@praison.ai>
License-Expression: MIT
License-File: LICENSE
Keywords: ai-agents,claude,cursor,llm,mcp,model-context-protocol,praisonai,tools
Classifier: Development Status :: 4 - Beta
Classifier: Intended Audience :: Developers
Classifier: License :: OSI Approved :: MIT License
Classifier: Programming Language :: Python :: 3
Classifier: Programming Language :: Python :: 3.10
Classifier: Programming Language :: Python :: 3.11
Classifier: Programming Language :: Python :: 3.12
Classifier: Topic :: Scientific/Engineering :: Artificial Intelligence
Requires-Python: >=3.10
Requires-Dist: mcp>=1.0.0
Requires-Dist: praisonaiagents>=0.0.80
Provides-Extra: all
Requires-Dist: starlette; extra == 'all'
Requires-Dist: uvicorn; extra == 'all'
Provides-Extra: sse
Requires-Dist: starlette; extra == 'sse'
Requires-Dist: uvicorn; extra == 'sse'
